pyqcstrc/__init__.py
pyqcstrc/dode2/__init__.py
pyqcstrc/dode2/intsct.py
pyqcstrc/dode2/math1.py
pyqcstrc/dode2/numericalc.py
pyqcstrc/dode2/occupation_domain.py
pyqcstrc/dode2/symmetry.py
pyqcstrc/dode2/two_occupation_domains.py
pyqcstrc/dode2/utils.py
pyqcstrc/ico2/__init__.py
pyqcstrc/ico2/intsct.py
pyqcstrc/ico2/math1.py
pyqcstrc/ico2/numericalc.py
pyqcstrc/ico2/occupation_domain.py
pyqcstrc/ico2/symmetry.py
pyqcstrc/ico2/two_occupation_domains.py
pyqcstrc/ico2/utils.py
pyqcstrc-0.0.2a10.dist-info/LICENSE.txt
pyqcstrc-0.0.2a10.dist-info/METADATA
pyqcstrc-0.0.2a10.dist-info/WHEEL
pyqcstrc-0.0.2a10.dist-info/top_level.txt
pyqcstrc-0.0.2a10.dist-info/RECORD
