Metadata-Version: 2.1
Name: pyqcstrc
Version: 0.0.2a10
Summary: PyQCstrc - Python library for Quasi-Crystal structure
Home-page: https://www.rs.tus.ac.jp/tsunetomo.yamada/pyqcstrc
Author: Tsunetomo Yamada
Author-email: tsunetomo.yamada@rs.tus.ac.jp
License: MIT
Classifier: Development Status :: 4 - Beta
Classifier: Intended Audience :: Developers
Classifier: Intended Audience :: Science/Research
Classifier: Intended Audience :: Education
Classifier: License :: OSI Approved :: MIT License
Classifier: Operating System :: MacOS :: MacOS X
Classifier: Operating System :: POSIX :: Linux
Classifier: Operating System :: Microsoft :: Windows :: Windows 10
Classifier: Programming Language :: Cython
Classifier: Programming Language :: Python :: 3.7
Classifier: Programming Language :: Python :: 3.8
Classifier: Programming Language :: Python :: 3.9
Classifier: Programming Language :: Python :: 3.10
Classifier: Programming Language :: Python :: 3.11
Classifier: Topic :: Scientific/Engineering :: Mathematics
Classifier: Topic :: Scientific/Engineering :: Physics
Requires-Python: >=3.7.0
License-File: LICENSE.txt
Requires-Dist: numpy >=1.20.0
Requires-Dist: scipy >=1.6.0
Provides-Extra: dev
Requires-Dist: notebook ; extra == 'dev'
Requires-Dist: matplotlib ; extra == 'dev'
Requires-Dist: ipython ; extra == 'dev'
Requires-Dist: ipykernel ; extra == 'dev'
